luminal/__init__.py
luminal/errors/__init__.py
luminal/errors/cleanup.py
luminal/errors/system.py
luminal/errors/threads.py
luminal/interfaces/__init__.py
luminal/interfaces/metadata.py
luminal/interfaces/photon.py
luminal/managers/__init__.py
luminal/managers/handler.py
luminal/managers/loader.py
luminal/managers/resolver.py
luminal/managers/threads.py
luminal/managers/tracer.py
luminal/tools/__init__.py
luminal/tools/colors.py
luminal/tools/logger.py
luminal/tools/sentinel.py
luminal/tools/utils.py
luminal-1.0.0.dist-info/LICENSE.txt
luminal-1.0.0.dist-info/METADATA
luminal-1.0.0.dist-info/WHEEL
luminal-1.0.0.dist-info/top_level.txt
luminal-1.0.0.dist-info/RECORD
