Metadata-Version: 2.1
Name: luminal
Version: 1.0.0
Summary: A lightweight, modular, and atomic photon, a.k.a plugin, loader.
Home-page: https://github.com/jasondrawdy/luminal
Author: Jason Drawdy
Author-email: luminalcodebase@protonmail.com
Project-URL: Documentation, https://luminal.readthedocs.io/en/latest/
Project-URL: Issue Tracker, https://github.com/jasondrawdy/luminal/issues
Keywords: actions,advanced logging,asynchronous,atomic,atomic reloading,branch,branch coverage,checksum,checksum algorithms,code,code statement coverage,comprehensive documentation,core features,couple,couple plugins,coupling plugins,coverage,customization,debugging,debugging methods,decouple,decouple plugins,decoupling plugins,dependencies,design,development,development time,documentation,dynamic,dynamic and modular design,dynamic framework,efficiency,efficient,efficient resource usage,error,er
Classifier: Development Status :: 3 - Alpha
Classifier: Intended Audience :: Developers
Classifier: License :: OSI Approved :: MIT License
Classifier: Programming Language :: Python :: 3
Classifier: Programming Language :: Python :: 3.6
Classifier: Programming Language :: Python :: 3.7
Classifier: Programming Language :: Python :: 3.8
Classifier: Programming Language :: Python :: 3.9
Classifier: Programming Language :: Python :: 3.10
Classifier: Programming Language :: Python :: 3.11
Classifier: Operating System :: OS Independent
License-File: LICENSE.txt
Provides-Extra: dev
Requires-Dist: coverage ; extra == 'dev'
Requires-Dist: twine ; extra == 'dev'
Requires-Dist: sphinx ; extra == 'dev'
Requires-Dist: sphinx-rtd-theme ; extra == 'dev'
Requires-Dist: sphinx-autoapi ; extra == 'dev'
